[
  {
    "id": 6215827348,
    "longitude": 78.0101931,
    "latitude": 11.7474516
  },
  {
    "id": 11259063557,
    "longitude": 78.144718,
    "latitude": 11.6082422
  },
  {
    "id": 3618349933,
    "longitude": 78.1665069,
    "latitude": 11.6817669
  },
  {
    "id": 2503902029,
    "longitude": 78.1042591,
    "latitude": 11.6122026
  },
  {
    "id": 11259282475,
    "longitude": 78.1290485,
    "latitude": 11.6098949
  },
  {
    "id": 12480951467,
    "longitude": 78.0822372,
    "latitude": 11.8767898
  },
  {
    "id": 4558948380,
    "longitude": 78.0136592,
    "latitude": 11.5696991
  },
  {
    "id": 9065446018,
    "longitude": 78.2369041,
    "latitude": 11.6732787
  },
  {
    "id": 12401928330,
    "longitude": 78.4917999,
    "latitude": 11.4406878
  },
  {
    "id": 2179331781,
    "longitude": 77.8387854,
    "latitude": 11.5788835
  }
]